{
  "configs": [
    {
      "id": 1710151840642,
      "configId": 1710151840642,
      "configName": "PLUG",
      "barrierElements": [
        {
          "id": "uI8k0H8_6bc82gkcD5J1Q",
          "name": "crown valve",
          "barrier": "secondary",
          "quantity": 1,
          "status": "pass"
        },
        {
          "id": "IqK5bB_jkxqkzqftUJxwv",
          "name": "surface safety valve",
          "barrier": "secondary",
          "quantity": 1,
          "status": null
        },
        {
          "id": "SsXaIwtunQp46daCfLq-h",
          "name": "safety valve control line",
          "barrier": "secondary",
          "quantity": 1,
          "status": null
        },
        {
          "id": "X9VDX-m88VITE9c0Q0DyY",
          "name": "wing valve",
          "barrier": "secondary",
          "quantity": 1,
          "status": null
        },
        {
          "id": "Zsy7RLM2KOXj_PPOkF6mm",
          "name": "lower master valve",
          "barrier": "secondary",
          "quantity": 1,
          "status": null
        },
        {
          "id": "mD4h65SA3mD-ySPZyxhaD",
          "name": "kill wing valve",
          "barrier": "secondary",
          "quantity": 1,
          "status": null
        },
        {
          "id": "kFxlihv8EneczFK66GIYU",
          "name": "production casing valves",
          "barrier": "secondary",
          "quantity": 2,
          "status": null
        },
        {
          "id": "VkTLCFd99eRDLaiPWhjzQ",
          "name": "intermediate casing",
          "barrier": "secondary",
          "quantity": 1,
          "status": null
        },
        {
          "id": "4BI-cC8e7OB5XYqXDfCk5",
          "name": "intermediate casing valves",
          "barrier": "secondary",
          "quantity": 2,
          "status": null
        },
        {
          "id": "G03imx8hXqI4r7o1ecLlE",
          "name": "cement ( intermediate casing )",
          "barrier": "secondary",
          "quantity": 1,
          "status": null
        },
        {
          "id": "LTCbNGQxM7diAez4xH1_i",
          "name": "surface casing",
          "barrier": "secondary",
          "quantity": 1,
          "status": null
        },
        {
          "id": "Sm3z1-kp1p4a6L5KfpK1O",
          "name": "surface casing valves",
          "barrier": "secondary",
          "quantity": 2,
          "status": null
        },
        {
          "id": "_ynFUHhbK3R40wQCEdnm_",
          "name": "cement ( surface casing )",
          "barrier": "secondary",
          "quantity": 1,
          "status": null
        },
        {
          "id": "S65I9lq_DjWYzlmkxwpJS",
          "name": "conductor casing",
          "barrier": "secondary",
          "quantity": 1,
          "status": null
        },
        {
          "id": "4Tg3neNgKxD_Q-GOJ4lOx",
          "name": "cement ( conductor casing )",
          "barrier": "secondary",
          "quantity": 1,
          "status": null
        },
        {
          "id": "cDyQeBdium4jV6IbjDTbf",
          "name": "conductor casing valves",
          "barrier": "none",
          "quantity": 0,
          "status": null
        },
        {
          "id": "77UES5yvffVqJSkLitmnC",
          "name": "casing hanger",
          "barrier": "secondary",
          "quantity": 1,
          "status": null
        },
        {
          "id": "g3oqRzvIOIKEjtxu9WTW5",
          "name": "tubing hanger",
          "barrier": "secondary",
          "quantity": 1,
          "status": null
        },
        {
          "id": "EI0Ni3R1q4qKhbwcicw0J",
          "name": "caprock",
          "barrier": "secondary",
          "quantity": 1,
          "status": null
        },
        {
          "id": "QhvUKQRmTp49AJPGZvcmz",
          "name": "void area",
          "barrier": "secondary",
          "quantity": 1,
          "status": null
        },
        {
          "id": "bfveNszwuJrokbxwM87fz",
          "name": "VR plug",
          "barrier": "none",
          "quantity": 0,
          "status": null
        },
        {
          "id": "Y7MDARunVtFP2fUeWMIOs",
          "name": "BPV / TWCV",
          "barrier": "none",
          "quantity": 0,
          "status": null
        },
        {
          "id": "Vu8Ye9WKpVEbt0nZkE2fO",
          "name": "production casing ( above packer )",
          "barrier": "secondary",
          "quantity": 1,
          "status": null
        },
        {
          "id": "HM7XYZE_BU8sytPmMKOnu",
          "name": "production casing ( below packer )",
          "barrier": "primary",
          "quantity": 1,
          "status": null
        },
        {
          "id": "mDid1M2x_tcfkF_PnNLJx",
          "name": "production tubing ( above DHSV )",
          "barrier": "secondary",
          "quantity": 1,
          "status": null
        },
        {
          "id": "l-Jhn33rFttnquPLBzv0T",
          "name": "production tubing ( below DHSV )",
          "barrier": "primary",
          "quantity": 1,
          "status": null
        },
        {
          "id": "9SxuZftBI_JZgq2ew33GN",
          "name": "cement ( production casing )",
          "barrier": "primary",
          "quantity": 1,
          "status": null
        },
        {
          "id": "xR5PQWOVJwFR9J0QEoHW9",
          "name": "downhole safety valve",
          "barrier": "primary",
          "quantity": 1,
          "status": null
        },
        {
          "id": "AIXcvTbKfHzk52YR02b-S",
          "name": "downhole safety valve control line",
          "barrier": "primary",
          "quantity": 1,
          "status": null
        },
        {
          "id": "dgrt5MsGozmBN08bx3fg9",
          "name": "downhole safety valve landing nipple",
          "barrier": "primary",
          "quantity": 1,
          "status": null
        },
        {
          "id": "5gK1cm229LGfvXquPFXuD",
          "name": "gas lift mandrel",
          "barrier": "none",
          "quantity": 0,
          "status": null
        },
        {
          "id": "BKsadxLiE8pBQ0L8yLgne",
          "name": "sliding side door",
          "barrier": "none",
          "quantity": 0,
          "status": null
        },
        {
          "id": "z3ZuxYl22Nc8m8wt5XCE1",
          "name": "production packer",
          "barrier": "primary",
          "quantity": 1,
          "status": null
        },
        {
          "id": "8H5b3_CtViDUZr7-nqQV8",
          "name": "tubing plug",
          "barrier": "primary",
          "quantity": 1,
          "status": null
        },
        {
          "id": "7zRc1OuDMIt9w11zJvDhO",
          "name": "in-situ formation",
          "barrier": "primary",
          "quantity": 1,
          "status": null
        }
      ]
    },
    {
      "id": 1710151871182,
      "configId": 1710151871182,
      "configName": "GLM",
      "barrierElements": [
        {
          "id": "uI8k0H8_6bc82gkcD5J1Q",
          "name": "crown valve",
          "barrier": "secondary",
          "quantity": 1,
          "status": "pass"
        },
        {
          "id": "IqK5bB_jkxqkzqftUJxwv",
          "name": "surface safety valve",
          "barrier": "secondary",
          "quantity": 1,
          "status": null
        },
        {
          "id": "SsXaIwtunQp46daCfLq-h",
          "name": "safety valve control line",
          "barrier": "secondary",
          "quantity": 1,
          "status": null
        },
        {
          "id": "X9VDX-m88VITE9c0Q0DyY",
          "name": "wing valve",
          "barrier": "secondary",
          "quantity": 1,
          "status": null
        },
        {
          "id": "Zsy7RLM2KOXj_PPOkF6mm",
          "name": "lower master valve",
          "barrier": "secondary",
          "quantity": 1,
          "status": null
        },
        {
          "id": "mD4h65SA3mD-ySPZyxhaD",
          "name": "kill wing valve",
          "barrier": "secondary",
          "quantity": 1,
          "status": null
        },
        {
          "id": "kFxlihv8EneczFK66GIYU",
          "name": "production casing valves",
          "barrier": "secondary",
          "quantity": 2,
          "status": null
        },
        {
          "id": "VkTLCFd99eRDLaiPWhjzQ",
          "name": "intermediate casing",
          "barrier": "secondary",
          "quantity": 1,
          "status": null
        },
        {
          "id": "4BI-cC8e7OB5XYqXDfCk5",
          "name": "intermediate casing valves",
          "barrier": "secondary",
          "quantity": 2,
          "status": null
        },
        {
          "id": "G03imx8hXqI4r7o1ecLlE",
          "name": "cement ( intermediate casing )",
          "barrier": "secondary",
          "quantity": 1,
          "status": null
        },
        {
          "id": "LTCbNGQxM7diAez4xH1_i",
          "name": "surface casing",
          "barrier": "secondary",
          "quantity": 1,
          "status": null
        },
        {
          "id": "Sm3z1-kp1p4a6L5KfpK1O",
          "name": "surface casing valves",
          "barrier": "secondary",
          "quantity": 2,
          "status": null
        },
        {
          "id": "_ynFUHhbK3R40wQCEdnm_",
          "name": "cement ( surface casing )",
          "barrier": "secondary",
          "quantity": 1,
          "status": null
        },
        {
          "id": "S65I9lq_DjWYzlmkxwpJS",
          "name": "conductor casing",
          "barrier": "secondary",
          "quantity": 1,
          "status": null
        },
        {
          "id": "4Tg3neNgKxD_Q-GOJ4lOx",
          "name": "cement ( conductor casing )",
          "barrier": "secondary",
          "quantity": 1,
          "status": null
        },
        {
          "id": "cDyQeBdium4jV6IbjDTbf",
          "name": "conductor casing valves",
          "barrier": "none",
          "quantity": 0,
          "status": null
        },
        {
          "id": "77UES5yvffVqJSkLitmnC",
          "name": "casing hanger",
          "barrier": "secondary",
          "quantity": 1,
          "status": null
        },
        {
          "id": "g3oqRzvIOIKEjtxu9WTW5",
          "name": "tubing hanger",
          "barrier": "secondary",
          "quantity": 1,
          "status": null
        },
        {
          "id": "EI0Ni3R1q4qKhbwcicw0J",
          "name": "caprock",
          "barrier": "secondary",
          "quantity": 1,
          "status": null
        },
        {
          "id": "QhvUKQRmTp49AJPGZvcmz",
          "name": "void area",
          "barrier": "secondary",
          "quantity": 1,
          "status": null
        },
        {
          "id": "bfveNszwuJrokbxwM87fz",
          "name": "VR plug",
          "barrier": "none",
          "quantity": 0,
          "status": null
        },
        {
          "id": "Y7MDARunVtFP2fUeWMIOs",
          "name": "BPV / TWCV",
          "barrier": "none",
          "quantity": 0,
          "status": null
        },
        {
          "id": "Vu8Ye9WKpVEbt0nZkE2fO",
          "name": "production casing ( above packer )",
          "barrier": "secondary",
          "quantity": 1,
          "status": null
        },
        {
          "id": "HM7XYZE_BU8sytPmMKOnu",
          "name": "production casing ( below packer )",
          "barrier": "primary",
          "quantity": 1,
          "status": null
        },
        {
          "id": "mDid1M2x_tcfkF_PnNLJx",
          "name": "production tubing ( above DHSV )",
          "barrier": "secondary",
          "quantity": 1,
          "status": null
        },
        {
          "id": "l-Jhn33rFttnquPLBzv0T",
          "name": "production tubing ( below DHSV )",
          "barrier": "primary",
          "quantity": 1,
          "status": null
        },
        {
          "id": "9SxuZftBI_JZgq2ew33GN",
          "name": "cement ( production casing )",
          "barrier": "primary",
          "quantity": 1,
          "status": null
        },
        {
          "id": "xR5PQWOVJwFR9J0QEoHW9",
          "name": "downhole safety valve",
          "barrier": "primary",
          "quantity": 1,
          "status": null
        },
        {
          "id": "AIXcvTbKfHzk52YR02b-S",
          "name": "downhole safety valve control line",
          "barrier": "primary",
          "quantity": 1,
          "status": null
        },
        {
          "id": "dgrt5MsGozmBN08bx3fg9",
          "name": "downhole safety valve landing nipple",
          "barrier": "primary",
          "quantity": 1,
          "status": null
        },
        {
          "id": "5gK1cm229LGfvXquPFXuD",
          "name": "gas lift mandrel",
          "barrier": "primary",
          "quantity": 5,
          "status": null
        },
        {
          "id": "BKsadxLiE8pBQ0L8yLgne",
          "name": "sliding side door",
          "barrier": "none",
          "quantity": 0,
          "status": null
        },
        {
          "id": "z3ZuxYl22Nc8m8wt5XCE1",
          "name": "production packer",
          "barrier": "primary",
          "quantity": 1,
          "status": null
        },
        {
          "id": "8H5b3_CtViDUZr7-nqQV8",
          "name": "tubing plug",
          "barrier": "none",
          "quantity": 0,
          "status": null
        },
        {
          "id": "7zRc1OuDMIt9w11zJvDhO",
          "name": "in-situ formation",
          "barrier": "primary",
          "quantity": 1,
          "status": null
        }
      ]
    },
    {
      "id": 1710151895004,
      "configId": 1710151895004,
      "configName": "SSD",
      "barrierElements": [
        {
          "id": "uI8k0H8_6bc82gkcD5J1Q",
          "name": "crown valve",
          "barrier": "secondary",
          "quantity": 1,
          "status": "pass"
        },
        {
          "id": "IqK5bB_jkxqkzqftUJxwv",
          "name": "surface safety valve",
          "barrier": "secondary",
          "quantity": 1,
          "status": null
        },
        {
          "id": "SsXaIwtunQp46daCfLq-h",
          "name": "safety valve control line",
          "barrier": "secondary",
          "quantity": 1,
          "status": null
        },
        {
          "id": "X9VDX-m88VITE9c0Q0DyY",
          "name": "wing valve",
          "barrier": "secondary",
          "quantity": 1,
          "status": null
        },
        {
          "id": "Zsy7RLM2KOXj_PPOkF6mm",
          "name": "lower master valve",
          "barrier": "secondary",
          "quantity": 1,
          "status": null
        },
        {
          "id": "mD4h65SA3mD-ySPZyxhaD",
          "name": "kill wing valve",
          "barrier": "secondary",
          "quantity": 1,
          "status": null
        },
        {
          "id": "kFxlihv8EneczFK66GIYU",
          "name": "production casing valves",
          "barrier": "secondary",
          "quantity": 2,
          "status": null
        },
        {
          "id": "VkTLCFd99eRDLaiPWhjzQ",
          "name": "intermediate casing",
          "barrier": "secondary",
          "quantity": 1,
          "status": null
        },
        {
          "id": "4BI-cC8e7OB5XYqXDfCk5",
          "name": "intermediate casing valves",
          "barrier": "secondary",
          "quantity": 2,
          "status": null
        },
        {
          "id": "G03imx8hXqI4r7o1ecLlE",
          "name": "cement ( intermediate casing )",
          "barrier": "secondary",
          "quantity": 1,
          "status": null
        },
        {
          "id": "LTCbNGQxM7diAez4xH1_i",
          "name": "surface casing",
          "barrier": "secondary",
          "quantity": 1,
          "status": null
        },
        {
          "id": "Sm3z1-kp1p4a6L5KfpK1O",
          "name": "surface casing valves",
          "barrier": "secondary",
          "quantity": 2,
          "status": null
        },
        {
          "id": "_ynFUHhbK3R40wQCEdnm_",
          "name": "cement ( surface casing )",
          "barrier": "secondary",
          "quantity": 1,
          "status": null
        },
        {
          "id": "S65I9lq_DjWYzlmkxwpJS",
          "name": "conductor casing",
          "barrier": "secondary",
          "quantity": 1,
          "status": null
        },
        {
          "id": "4Tg3neNgKxD_Q-GOJ4lOx",
          "name": "cement ( conductor casing )",
          "barrier": "secondary",
          "quantity": 1,
          "status": null
        },
        {
          "id": "cDyQeBdium4jV6IbjDTbf",
          "name": "conductor casing valves",
          "barrier": "none",
          "quantity": 0,
          "status": null
        },
        {
          "id": "77UES5yvffVqJSkLitmnC",
          "name": "casing hanger",
          "barrier": "secondary",
          "quantity": 1,
          "status": null
        },
        {
          "id": "g3oqRzvIOIKEjtxu9WTW5",
          "name": "tubing hanger",
          "barrier": "secondary",
          "quantity": 1,
          "status": null
        },
        {
          "id": "EI0Ni3R1q4qKhbwcicw0J",
          "name": "caprock",
          "barrier": "secondary",
          "quantity": 1,
          "status": null
        },
        {
          "id": "QhvUKQRmTp49AJPGZvcmz",
          "name": "void area",
          "barrier": "secondary",
          "quantity": 1,
          "status": null
        },
        {
          "id": "bfveNszwuJrokbxwM87fz",
          "name": "VR plug",
          "barrier": "none",
          "quantity": 0,
          "status": null
        },
        {
          "id": "Y7MDARunVtFP2fUeWMIOs",
          "name": "BPV / TWCV",
          "barrier": "none",
          "quantity": 0,
          "status": null
        },
        {
          "id": "Vu8Ye9WKpVEbt0nZkE2fO",
          "name": "production casing ( above packer )",
          "barrier": "secondary",
          "quantity": 1,
          "status": null
        },
        {
          "id": "HM7XYZE_BU8sytPmMKOnu",
          "name": "production casing ( below packer )",
          "barrier": "primary",
          "quantity": 1,
          "status": null
        },
        {
          "id": "mDid1M2x_tcfkF_PnNLJx",
          "name": "production tubing ( above DHSV )",
          "barrier": "secondary",
          "quantity": 1,
          "status": null
        },
        {
          "id": "l-Jhn33rFttnquPLBzv0T",
          "name": "production tubing ( below DHSV )",
          "barrier": "primary",
          "quantity": 1,
          "status": null
        },
        {
          "id": "9SxuZftBI_JZgq2ew33GN",
          "name": "cement ( production casing )",
          "barrier": "primary",
          "quantity": 1,
          "status": null
        },
        {
          "id": "xR5PQWOVJwFR9J0QEoHW9",
          "name": "downhole safety valve",
          "barrier": "primary",
          "quantity": 1,
          "status": null
        },
        {
          "id": "AIXcvTbKfHzk52YR02b-S",
          "name": "downhole safety valve control line",
          "barrier": "primary",
          "quantity": 1,
          "status": null
        },
        {
          "id": "dgrt5MsGozmBN08bx3fg9",
          "name": "downhole safety valve landing nipple",
          "barrier": "primary",
          "quantity": 1,
          "status": null
        },
        {
          "id": "5gK1cm229LGfvXquPFXuD",
          "name": "gas lift mandrel",
          "barrier": "none",
          "quantity": 0,
          "status": null
        },
        {
          "id": "BKsadxLiE8pBQ0L8yLgne",
          "name": "sliding side door",
          "barrier": "primary",
          "quantity": 3,
          "status": null
        },
        {
          "id": "z3ZuxYl22Nc8m8wt5XCE1",
          "name": "production packer",
          "barrier": "primary",
          "quantity": 1,
          "status": null
        },
        {
          "id": "8H5b3_CtViDUZr7-nqQV8",
          "name": "tubing plug",
          "barrier": "none",
          "quantity": 0,
          "status": null
        },
        {
          "id": "7zRc1OuDMIt9w11zJvDhO",
          "name": "in-situ formation",
          "barrier": "primary",
          "quantity": 1,
          "status": null
        }
      ]
    }
  ],
  "wells": [
    {
      "id": 1710151996711,
      "wellName": "Resak A1U",
      "configs": [
        {
          "cdftDate": null,
          "preventiveMaintenanceId": null,
          "configId": 1709718224354,
          "configName": "PLUG",
          "updatedAt": 1710151996711,
          "barrierElements": [
            {
              "id": "uI8k0H8_6bc82gkcD5J1Q",
              "name": "crown valve",
              "barrier": "secondary",
              "quantity": 1,
              "status": "pass"
            },
            {
              "id": "IqK5bB_jkxqkzqftUJxwv",
              "name": "surface safety valve",
              "barrier": "secondary",
              "quantity": 1,
              "status": null
            },
            {
              "id": "SsXaIwtunQp46daCfLq-h",
              "name": "safety valve control line",
              "barrier": "secondary",
              "quantity": 1,
              "status": null
            },
            {
              "id": "X9VDX-m88VITE9c0Q0DyY",
              "name": "wing valve",
              "barrier": "secondary",
              "quantity": 1,
              "status": null
            },
            {
              "id": "Zsy7RLM2KOXj_PPOkF6mm",
              "name": "lower master valve",
              "barrier": "secondary",
              "quantity": 1,
              "status": null
            },
            {
              "id": "mD4h65SA3mD-ySPZyxhaD",
              "name": "kill wing valve",
              "barrier": "secondary",
              "quantity": 1,
              "status": null
            },
            {
              "id": "kFxlihv8EneczFK66GIYU",
              "name": "production casing valves",
              "barrier": "secondary",
              "quantity": 2,
              "status": null
            },
            {
              "id": "VkTLCFd99eRDLaiPWhjzQ",
              "name": "intermediate casing",
              "barrier": "secondary",
              "quantity": 1,
              "status": null
            },
            {
              "id": "4BI-cC8e7OB5XYqXDfCk5",
              "name": "intermediate casing valves",
              "barrier": "secondary",
              "quantity": 2,
              "status": null
            },
            {
              "id": "G03imx8hXqI4r7o1ecLlE",
              "name": "cement ( intermediate casing )",
              "barrier": "secondary",
              "quantity": 1,
              "status": null
            },
            {
              "id": "LTCbNGQxM7diAez4xH1_i",
              "name": "surface casing",
              "barrier": "secondary",
              "quantity": 1,
              "status": null
            },
            {
              "id": "Sm3z1-kp1p4a6L5KfpK1O",
              "name": "surface casing valves",
              "barrier": "secondary",
              "quantity": 2,
              "status": null
            },
            {
              "id": "_ynFUHhbK3R40wQCEdnm_",
              "name": "cement ( surface casing )",
              "barrier": "secondary",
              "quantity": 1,
              "status": null
            },
            {
              "id": "S65I9lq_DjWYzlmkxwpJS",
              "name": "conductor casing",
              "barrier": "secondary",
              "quantity": 1,
              "status": null
            },
            {
              "id": "4Tg3neNgKxD_Q-GOJ4lOx",
              "name": "cement ( conductor casing )",
              "barrier": "secondary",
              "quantity": 1,
              "status": null
            },
            {
              "id": "cDyQeBdium4jV6IbjDTbf",
              "name": "conductor casing valves",
              "barrier": "none",
              "quantity": 0,
              "status": null
            },
            {
              "id": "77UES5yvffVqJSkLitmnC",
              "name": "casing hanger",
              "barrier": "secondary",
              "quantity": 1,
              "status": null
            },
            {
              "id": "g3oqRzvIOIKEjtxu9WTW5",
              "name": "tubing hanger",
              "barrier": "secondary",
              "quantity": 1,
              "status": null
            },
            {
              "id": "EI0Ni3R1q4qKhbwcicw0J",
              "name": "caprock",
              "barrier": "secondary",
              "quantity": 1,
              "status": null
            },
            {
              "id": "QhvUKQRmTp49AJPGZvcmz",
              "name": "void area",
              "barrier": "secondary",
              "quantity": 1,
              "status": null
            },
            {
              "id": "bfveNszwuJrokbxwM87fz",
              "name": "VR plug",
              "barrier": "none",
              "quantity": 0,
              "status": null
            },
            {
              "id": "Y7MDARunVtFP2fUeWMIOs",
              "name": "BPV / TWCV",
              "barrier": "none",
              "quantity": 0,
              "status": null
            },
            {
              "id": "Vu8Ye9WKpVEbt0nZkE2fO",
              "name": "production casing ( above packer )",
              "barrier": "secondary",
              "quantity": 1,
              "status": null
            },
            {
              "id": "HM7XYZE_BU8sytPmMKOnu",
              "name": "production casing ( below packer )",
              "barrier": "primary",
              "quantity": 1,
              "status": null
            },
            {
              "id": "mDid1M2x_tcfkF_PnNLJx",
              "name": "production tubing ( above DHSV )",
              "barrier": "secondary",
              "quantity": 1,
              "status": null
            },
            {
              "id": "l-Jhn33rFttnquPLBzv0T",
              "name": "production tubing ( below DHSV )",
              "barrier": "primary",
              "quantity": 1,
              "status": null
            },
            {
              "id": "9SxuZftBI_JZgq2ew33GN",
              "name": "cement ( production casing )",
              "barrier": "primary",
              "quantity": 1,
              "status": null
            },
            {
              "id": "xR5PQWOVJwFR9J0QEoHW9",
              "name": "downhole safety valve",
              "barrier": "primary",
              "quantity": 1,
              "status": null
            },
            {
              "id": "AIXcvTbKfHzk52YR02b-S",
              "name": "downhole safety valve control line",
              "barrier": "primary",
              "quantity": 1,
              "status": null
            },
            {
              "id": "dgrt5MsGozmBN08bx3fg9",
              "name": "downhole safety valve landing nipple",
              "barrier": "primary",
              "quantity": 1,
              "status": null
            },
            {
              "id": "5gK1cm229LGfvXquPFXuD",
              "name": "gas lift mandrel",
              "barrier": "none",
              "quantity": 0,
              "status": null
            },
            {
              "id": "BKsadxLiE8pBQ0L8yLgne",
              "name": "sliding side door",
              "barrier": "none",
              "quantity": 0,
              "status": null
            },
            {
              "id": "z3ZuxYl22Nc8m8wt5XCE1",
              "name": "production packer",
              "barrier": "primary",
              "quantity": 1,
              "status": null
            },
            {
              "id": "8H5b3_CtViDUZr7-nqQV8",
              "name": "tubing plug",
              "barrier": "primary",
              "quantity": 1,
              "status": null
            },
            {
              "id": "7zRc1OuDMIt9w11zJvDhO",
              "name": "in-situ formation",
              "barrier": "primary",
              "quantity": 1,
              "status": null
            }
          ]
        },
        {
          "cdftDate": null,
          "preventiveMaintenanceId": null,
          "updatedAt": 1710152008865,
          "id": 1710151871182,
          "configId": 1710151871182,
          "configName": "GLM",
          "barrierElements": [
            {
              "id": "uI8k0H8_6bc82gkcD5J1Q",
              "name": "crown valve",
              "barrier": "secondary",
              "quantity": 1,
              "status": "pass"
            },
            {
              "id": "IqK5bB_jkxqkzqftUJxwv",
              "name": "surface safety valve",
              "barrier": "secondary",
              "quantity": 1,
              "status": null
            },
            {
              "id": "SsXaIwtunQp46daCfLq-h",
              "name": "safety valve control line",
              "barrier": "secondary",
              "quantity": 1,
              "status": null
            },
            {
              "id": "X9VDX-m88VITE9c0Q0DyY",
              "name": "wing valve",
              "barrier": "secondary",
              "quantity": 1,
              "status": null
            },
            {
              "id": "Zsy7RLM2KOXj_PPOkF6mm",
              "name": "lower master valve",
              "barrier": "secondary",
              "quantity": 1,
              "status": null
            },
            {
              "id": "mD4h65SA3mD-ySPZyxhaD",
              "name": "kill wing valve",
              "barrier": "secondary",
              "quantity": 1,
              "status": null
            },
            {
              "id": "kFxlihv8EneczFK66GIYU",
              "name": "production casing valves",
              "barrier": "secondary",
              "quantity": 2,
              "status": null
            },
            {
              "id": "VkTLCFd99eRDLaiPWhjzQ",
              "name": "intermediate casing",
              "barrier": "secondary",
              "quantity": 1,
              "status": null
            },
            {
              "id": "4BI-cC8e7OB5XYqXDfCk5",
              "name": "intermediate casing valves",
              "barrier": "secondary",
              "quantity": 2,
              "status": null
            },
            {
              "id": "G03imx8hXqI4r7o1ecLlE",
              "name": "cement ( intermediate casing )",
              "barrier": "secondary",
              "quantity": 1,
              "status": null
            },
            {
              "id": "LTCbNGQxM7diAez4xH1_i",
              "name": "surface casing",
              "barrier": "secondary",
              "quantity": 1,
              "status": null
            },
            {
              "id": "Sm3z1-kp1p4a6L5KfpK1O",
              "name": "surface casing valves",
              "barrier": "secondary",
              "quantity": 2,
              "status": null
            },
            {
              "id": "_ynFUHhbK3R40wQCEdnm_",
              "name": "cement ( surface casing )",
              "barrier": "secondary",
              "quantity": 1,
              "status": null
            },
            {
              "id": "S65I9lq_DjWYzlmkxwpJS",
              "name": "conductor casing",
              "barrier": "secondary",
              "quantity": 1,
              "status": null
            },
            {
              "id": "4Tg3neNgKxD_Q-GOJ4lOx",
              "name": "cement ( conductor casing )",
              "barrier": "secondary",
              "quantity": 1,
              "status": null
            },
            {
              "id": "cDyQeBdium4jV6IbjDTbf",
              "name": "conductor casing valves",
              "barrier": "none",
              "quantity": 0,
              "status": null
            },
            {
              "id": "77UES5yvffVqJSkLitmnC",
              "name": "casing hanger",
              "barrier": "secondary",
              "quantity": 1,
              "status": null
            },
            {
              "id": "g3oqRzvIOIKEjtxu9WTW5",
              "name": "tubing hanger",
              "barrier": "secondary",
              "quantity": 1,
              "status": null
            },
            {
              "id": "EI0Ni3R1q4qKhbwcicw0J",
              "name": "caprock",
              "barrier": "secondary",
              "quantity": 1,
              "status": null
            },
            {
              "id": "QhvUKQRmTp49AJPGZvcmz",
              "name": "void area",
              "barrier": "secondary",
              "quantity": 1,
              "status": null
            },
            {
              "id": "bfveNszwuJrokbxwM87fz",
              "name": "VR plug",
              "barrier": "none",
              "quantity": 0,
              "status": null
            },
            {
              "id": "Y7MDARunVtFP2fUeWMIOs",
              "name": "BPV / TWCV",
              "barrier": "none",
              "quantity": 0,
              "status": null
            },
            {
              "id": "Vu8Ye9WKpVEbt0nZkE2fO",
              "name": "production casing ( above packer )",
              "barrier": "secondary",
              "quantity": 1,
              "status": null
            },
            {
              "id": "HM7XYZE_BU8sytPmMKOnu",
              "name": "production casing ( below packer )",
              "barrier": "primary",
              "quantity": 1,
              "status": null
            },
            {
              "id": "mDid1M2x_tcfkF_PnNLJx",
              "name": "production tubing ( above DHSV )",
              "barrier": "secondary",
              "quantity": 1,
              "status": null
            },
            {
              "id": "l-Jhn33rFttnquPLBzv0T",
              "name": "production tubing ( below DHSV )",
              "barrier": "primary",
              "quantity": 1,
              "status": null
            },
            {
              "id": "9SxuZftBI_JZgq2ew33GN",
              "name": "cement ( production casing )",
              "barrier": "primary",
              "quantity": 1,
              "status": null
            },
            {
              "id": "xR5PQWOVJwFR9J0QEoHW9",
              "name": "downhole safety valve",
              "barrier": "primary",
              "quantity": 1,
              "status": null
            },
            {
              "id": "AIXcvTbKfHzk52YR02b-S",
              "name": "downhole safety valve control line",
              "barrier": "primary",
              "quantity": 1,
              "status": null
            },
            {
              "id": "dgrt5MsGozmBN08bx3fg9",
              "name": "downhole safety valve landing nipple",
              "barrier": "primary",
              "quantity": 1,
              "status": null
            },
            {
              "id": "5gK1cm229LGfvXquPFXuD",
              "name": "gas lift mandrel",
              "barrier": "primary",
              "quantity": 5,
              "status": null
            },
            {
              "id": "BKsadxLiE8pBQ0L8yLgne",
              "name": "sliding side door",
              "barrier": "none",
              "quantity": 0,
              "status": null
            },
            {
              "id": "z3ZuxYl22Nc8m8wt5XCE1",
              "name": "production packer",
              "barrier": "primary",
              "quantity": 1,
              "status": null
            },
            {
              "id": "8H5b3_CtViDUZr7-nqQV8",
              "name": "tubing plug",
              "barrier": "none",
              "quantity": 0,
              "status": null
            },
            {
              "id": "7zRc1OuDMIt9w11zJvDhO",
              "name": "in-situ formation",
              "barrier": "primary",
              "quantity": 1,
              "status": null
            }
          ]
        },
        {
          "cdftDate": null,
          "preventiveMaintenanceId": null,
          "updatedAt": 1710152015607,
          "id": 1710151895004,
          "configId": 1710151895004,
          "configName": "SSD",
          "barrierElements": [
            {
              "id": "uI8k0H8_6bc82gkcD5J1Q",
              "name": "crown valve",
              "barrier": "secondary",
              "quantity": 1,
              "status": "pass"
            },
            {
              "id": "IqK5bB_jkxqkzqftUJxwv",
              "name": "surface safety valve",
              "barrier": "secondary",
              "quantity": 1,
              "status": null
            },
            {
              "id": "SsXaIwtunQp46daCfLq-h",
              "name": "safety valve control line",
              "barrier": "secondary",
              "quantity": 1,
              "status": null
            },
            {
              "id": "X9VDX-m88VITE9c0Q0DyY",
              "name": "wing valve",
              "barrier": "secondary",
              "quantity": 1,
              "status": null
            },
            {
              "id": "Zsy7RLM2KOXj_PPOkF6mm",
              "name": "lower master valve",
              "barrier": "secondary",
              "quantity": 1,
              "status": null
            },
            {
              "id": "mD4h65SA3mD-ySPZyxhaD",
              "name": "kill wing valve",
              "barrier": "secondary",
              "quantity": 1,
              "status": null
            },
            {
              "id": "kFxlihv8EneczFK66GIYU",
              "name": "production casing valves",
              "barrier": "secondary",
              "quantity": 2,
              "status": null
            },
            {
              "id": "VkTLCFd99eRDLaiPWhjzQ",
              "name": "intermediate casing",
              "barrier": "secondary",
              "quantity": 1,
              "status": null
            },
            {
              "id": "4BI-cC8e7OB5XYqXDfCk5",
              "name": "intermediate casing valves",
              "barrier": "secondary",
              "quantity": 2,
              "status": null
            },
            {
              "id": "G03imx8hXqI4r7o1ecLlE",
              "name": "cement ( intermediate casing )",
              "barrier": "secondary",
              "quantity": 1,
              "status": null
            },
            {
              "id": "LTCbNGQxM7diAez4xH1_i",
              "name": "surface casing",
              "barrier": "secondary",
              "quantity": 1,
              "status": null
            },
            {
              "id": "Sm3z1-kp1p4a6L5KfpK1O",
              "name": "surface casing valves",
              "barrier": "secondary",
              "quantity": 2,
              "status": null
            },
            {
              "id": "_ynFUHhbK3R40wQCEdnm_",
              "name": "cement ( surface casing )",
              "barrier": "secondary",
              "quantity": 1,
              "status": null
            },
            {
              "id": "S65I9lq_DjWYzlmkxwpJS",
              "name": "conductor casing",
              "barrier": "secondary",
              "quantity": 1,
              "status": null
            },
            {
              "id": "4Tg3neNgKxD_Q-GOJ4lOx",
              "name": "cement ( conductor casing )",
              "barrier": "secondary",
              "quantity": 1,
              "status": null
            },
            {
              "id": "cDyQeBdium4jV6IbjDTbf",
              "name": "conductor casing valves",
              "barrier": "none",
              "quantity": 0,
              "status": null
            },
            {
              "id": "77UES5yvffVqJSkLitmnC",
              "name": "casing hanger",
              "barrier": "secondary",
              "quantity": 1,
              "status": null
            },
            {
              "id": "g3oqRzvIOIKEjtxu9WTW5",
              "name": "tubing hanger",
              "barrier": "secondary",
              "quantity": 1,
              "status": null
            },
            {
              "id": "EI0Ni3R1q4qKhbwcicw0J",
              "name": "caprock",
              "barrier": "secondary",
              "quantity": 1,
              "status": null
            },
            {
              "id": "QhvUKQRmTp49AJPGZvcmz",
              "name": "void area",
              "barrier": "secondary",
              "quantity": 1,
              "status": null
            },
            {
              "id": "bfveNszwuJrokbxwM87fz",
              "name": "VR plug",
              "barrier": "none",
              "quantity": 0,
              "status": null
            },
            {
              "id": "Y7MDARunVtFP2fUeWMIOs",
              "name": "BPV / TWCV",
              "barrier": "none",
              "quantity": 0,
              "status": null
            },
            {
              "id": "Vu8Ye9WKpVEbt0nZkE2fO",
              "name": "production casing ( above packer )",
              "barrier": "secondary",
              "quantity": 1,
              "status": null
            },
            {
              "id": "HM7XYZE_BU8sytPmMKOnu",
              "name": "production casing ( below packer )",
              "barrier": "primary",
              "quantity": 1,
              "status": null
            },
            {
              "id": "mDid1M2x_tcfkF_PnNLJx",
              "name": "production tubing ( above DHSV )",
              "barrier": "secondary",
              "quantity": 1,
              "status": null
            },
            {
              "id": "l-Jhn33rFttnquPLBzv0T",
              "name": "production tubing ( below DHSV )",
              "barrier": "primary",
              "quantity": 1,
              "status": null
            },
            {
              "id": "9SxuZftBI_JZgq2ew33GN",
              "name": "cement ( production casing )",
              "barrier": "primary",
              "quantity": 1,
              "status": null
            },
            {
              "id": "xR5PQWOVJwFR9J0QEoHW9",
              "name": "downhole safety valve",
              "barrier": "primary",
              "quantity": 1,
              "status": null
            },
            {
              "id": "AIXcvTbKfHzk52YR02b-S",
              "name": "downhole safety valve control line",
              "barrier": "primary",
              "quantity": 1,
              "status": null
            },
            {
              "id": "dgrt5MsGozmBN08bx3fg9",
              "name": "downhole safety valve landing nipple",
              "barrier": "primary",
              "quantity": 1,
              "status": null
            },
            {
              "id": "5gK1cm229LGfvXquPFXuD",
              "name": "gas lift mandrel",
              "barrier": "none",
              "quantity": 0,
              "status": null
            },
            {
              "id": "BKsadxLiE8pBQ0L8yLgne",
              "name": "sliding side door",
              "barrier": "primary",
              "quantity": 3,
              "status": null
            },
            {
              "id": "z3ZuxYl22Nc8m8wt5XCE1",
              "name": "production packer",
              "barrier": "primary",
              "quantity": 1,
              "status": null
            },
            {
              "id": "8H5b3_CtViDUZr7-nqQV8",
              "name": "tubing plug",
              "barrier": "none",
              "quantity": 0,
              "status": null
            },
            {
              "id": "7zRc1OuDMIt9w11zJvDhO",
              "name": "in-situ formation",
              "barrier": "primary",
              "quantity": 1,
              "status": null
            }
          ]
        }
      ]
    }
  ]
}